databricks/__init__.py
databricks/vector_search/__init__.py
databricks/vector_search/client.py
databricks/vector_search/exceptions.py
databricks/vector_search/index.py
databricks/vector_search/reranker.py
databricks/vector_search/utils.py
databricks/vector_search/version.py
databricks_vectorsearch-0.64.dist-info/LICENSE.md
databricks_vectorsearch-0.64.dist-info/METADATA
databricks_vectorsearch-0.64.dist-info/WHEEL
databricks_vectorsearch-0.64.dist-info/top_level.txt
databricks_vectorsearch-0.64.dist-info/RECORD
