Metadata-Version: 2.1
Name: databricks-vectorsearch
Version: 0.64
Summary: Databricks Vector Search Client
Home-page: UNKNOWN
Author: Databricks
Author-email: feedback@databricks.com
License: UNKNOWN
Platform: UNKNOWN
Requires-Python: >=3.7
Requires-Dist: deprecation (>=2)
Requires-Dist: mlflow-skinny (<4,>=2.11.3)
Requires-Dist: protobuf (<7,>=3.12.0)
Requires-Dist: requests (>=2)
